VCFRIDER/__init__.py
VCFRIDER/vcfrider.py
VCFRIDER-1.1.0.dist-info/METADATA
VCFRIDER-1.1.0.dist-info/WHEEL
VCFRIDER-1.1.0.dist-info/top_level.txt
VCFRIDER-1.1.0.dist-info/RECORD
