Metadata-Version: 2.1
Name: VCFRIDER
Version: 1.1.0
Summary: VCFRIDER python for VCF data analysis
Home-page: https://github.com/sasurasa/VCFRIDER/tree/main.
Author: Surasak Sangkhathat
Author-email: s.sangkhathat@gmail.com
License: Prince of Songkla University
Platform: UNKNOWN
